README.md
setup.py
mct_sdk/__init__.py
mct_sdk/client.py
mct_sdk.egg-info/PKG-INFO
mct_sdk.egg-info/SOURCES.txt
mct_sdk.egg-info/dependency_links.txt
mct_sdk.egg-info/requires.txt
mct_sdk.egg-info/top_level.txt