Metadata-Version: 1.0
Name: mct-sdk
Version: 1.3.2
Summary: MCT python SKD
Home-page: https://github.com/mine-top/mct_python_sdk
Author: IO-HOST DEV
Author-email: admin@alexue4.ru
License: Creative Commons Attribution-Noncommercial-Share Alike license
Platform: UNKNOWN
